enboard/__init__.py
enboard/__main__.py
enboard/conda-bashrc-mingw.sh
enboard/conda-bashrc.sh
enboard/envs.py
enboard/menu.py
enboard-0.6.dist-info/entry_points.txt
enboard-0.6.dist-info/LICENSE
enboard-0.6.dist-info/WHEEL
enboard-0.6.dist-info/METADATA
enboard-0.6.dist-info/RECORD
